{
  "name": "moomin",
  "version": "0.1.0-alpha.1",
  "bsc-flags": ["-bs-super-errors", "-bs-no-version-header"],
  "bs-dependencies": [
    "wonka",
    "Reasongl"
  ],
  "package-specs": [{
    "module": "commonjs",
    "in-source": false
  }, {
    "module": "es6",
    "in-source": false
  }],
  "sources": [{
    "dir": "src",
    "subdirs": [{
      "dir": "reprocessing",
      "subdirs": [{
        "dir": "bytecode",
        "backend": ["bytecode"]
      }]
    }]
  }],
  "namespace": false,
  "refmt": 3,
  "reason": {
    "react-jsx": 2
  }
}
